qtfluentwidgets/__init__.py
qtfluentwidgets/_rc/__init__.py
qtfluentwidgets/_rc/images/acrylic/noise.png
qtfluentwidgets/_rc/images/check_box/Accept_black.svg
qtfluentwidgets/_rc/images/check_box/Accept_white.svg
qtfluentwidgets/_rc/images/check_box/PartialAccept_black.svg
qtfluentwidgets/_rc/images/check_box/PartialAccept_white.svg
qtfluentwidgets/_rc/images/color_dialog/Clear_black.svg
qtfluentwidgets/_rc/images/color_dialog/Clear_white.svg
qtfluentwidgets/_rc/images/color_dialog/HuePanel.png
qtfluentwidgets/_rc/images/folder_list_dialog/Add_black.png
qtfluentwidgets/_rc/images/folder_list_dialog/Add_white.png
qtfluentwidgets/_rc/images/folder_list_dialog/Close_black.png
qtfluentwidgets/_rc/images/folder_list_dialog/Close_white.png
qtfluentwidgets/_rc/images/icons/Add_black.svg
qtfluentwidgets/_rc/images/icons/Add_white.svg
qtfluentwidgets/_rc/images/icons/Album_black.svg
qtfluentwidgets/_rc/images/icons/Album_white.svg
qtfluentwidgets/_rc/images/icons/Alignment_black.svg
qtfluentwidgets/_rc/images/icons/Alignment_white.svg
qtfluentwidgets/_rc/images/icons/BackgroundColor_black.svg
qtfluentwidgets/_rc/images/icons/BackgroundColor_white.svg
qtfluentwidgets/_rc/images/icons/BookShelf_black.svg
qtfluentwidgets/_rc/images/icons/BookShelf_white.svg
qtfluentwidgets/_rc/images/icons/Brush_black.svg
qtfluentwidgets/_rc/images/icons/Brush_white.svg
qtfluentwidgets/_rc/images/icons/Camera_black.svg
qtfluentwidgets/_rc/images/icons/Camera_white.svg
qtfluentwidgets/_rc/images/icons/Cancel_black.svg
qtfluentwidgets/_rc/images/icons/Cancel_white.svg
qtfluentwidgets/_rc/images/icons/Chat_black.svg
qtfluentwidgets/_rc/images/icons/Chat_white.svg
qtfluentwidgets/_rc/images/icons/CheckBox_black.svg
qtfluentwidgets/_rc/images/icons/CheckBox_white.svg
qtfluentwidgets/_rc/images/icons/ChevronDown_black.svg
qtfluentwidgets/_rc/images/icons/ChevronDown_white.svg
qtfluentwidgets/_rc/images/icons/ChevronRight_black.svg
qtfluentwidgets/_rc/images/icons/ChevronRight_white.svg
QtPy_Fluent_Widgets-0.0.3.dist-info/WHEEL
QtPy_Fluent_Widgets-0.0.3.dist-info/METADATA
QtPy_Fluent_Widgets-0.0.3.dist-info/licenses/LICENSE
QtPy_Fluent_Widgets-0.0.3.dist-info/RECORD
