Metadata-Version: 2.1
Name: QtPy-Fluent-Widgets
Version: 0.0.3
Summary: A fluent design widgets library based on QtPy
License: GPLv3
Keywords: qtpy fluent widgets
Author-email: TaoChenyue <3038816978@qq.com>,zhiyiYo <shokokawaii@outlook.com>
Requires-Python: >=3.7,<3.10
Classifier: License :: OSI Approved :: GNU General Public License v3 (GPLv3)
Classifier: Operating System :: OS Independent
Classifier: Programming Language :: Python :: 3
Requires-Dist: QtPy
Requires-Dist: QtPy-Frameless-Window
Requires-Dist: darkdetect
Provides-Extra: full
Requires-Dist: colorthief; extra == "full"
Requires-Dist: pillow; extra == "full"
Requires-Dist: scipy; extra == "full"
Provides-Extra: pyqt
Requires-Dist: pyside2>=5.15.2.1; extra == "pyqt"
Requires-Dist: pyside6>=6.5.0; extra == "pyqt"
Requires-Dist: pyqt5>=5.15.9; extra == "pyqt"
Requires-Dist: pyqt6>=6.4.2; extra == "pyqt"
Project-URL: Documentation, https://pyqt-fluent-widgets.readthedocs.io/
Project-URL: Homepage, https://github.com/TaoChenyue/QtPy-Fluent-Widgets
